phoney_dictate/__init__.py
phoney_dictate/__main__.py
phoney_dictate/qrcode.py
phoney_dictate/res/favicon.ico
phoney_dictate/res/interface.html
phoney_dictate/res/main_window.ui
phoney_dictate/res/phoney-dicate.desktop
phoney_dictate/res/phoney-dicate.png
phoney_dictate/res/phoney-dicate.svg
phoney_dictate/res/qrcode.svg
phoney_dictate-1.1.1.dist-info/entry_points.txt
phoney_dictate-1.1.1.dist-info/LICENSE
phoney_dictate-1.1.1.dist-info/WHEEL
phoney_dictate-1.1.1.dist-info/METADATA
phoney_dictate-1.1.1.dist-info/RECORD
