Metadata-Version: 2.1
Name: phoney_dictate
Version: 1.1.1
Summary: A voice recognition "app" which sends your cell phone's voice recognition input to your computer.
Author-email: Leon Dionne <ldionne@dridesign.sh.cn>
Classifier: License :: OSI Approved :: GNU General Public License v3 or later (GPLv3+)
Requires-Dist: PyQt5
Requires-Dist: qrcodegen
Requires-Dist: soso_qt_extras >= 1.2.0
Project-URL: Home, https://github.com/Zen-Master-SoSo/phoney_dictate
